{
  "packageId": "com.chartworkspace.game",
  "host": "mindmapper.qzz.io",
  "name": "ChartWorkspace Game",
  "launcherName": "CW Game",
  "display": "standalone",
  "themeColor": "#0a0f1f",
  "navigationColor": "#0a0f1f",
  "backgroundColor": "#0a0f1f",
  "startUrl": "https://mindmapper.qzz.io/game",
  "scope": "/game",
  "webManifestUrl": "https://mindmapper.qzz.io/manifest.webmanifest",
  "iconUrl": "https://mindmapper.qzz.io/favicon.ico",
  "maskableIconUrl": "https://mindmapper.qzz.io/favicon.ico",
  "monochromeIconUrl": "https://mindmapper.qzz.io/favicon.ico",
  "fallbackType": "customtabs",
  "enableNotifications": false,
  "appVersionName": "1.0.0",
  "appVersionCode": 1,
  "generatorApp": "bubblewrap",
  "intentFilters": [
    {
      "action": "VIEW",
      "autoVerify": true,
      "categories": ["BROWSABLE", "DEFAULT"],
      "data": [
        {
          "scheme": "https",
          "host": "mindmapper.qzz.io",
          "pathPrefix": "/game"
        }
      ]
    }
  ]
}
